{
    "DATA_SECTION": "",
    "HEADER": {
        "COMMENTS": {
            "Best known objective": "",
            "Computational time (s)": "",
            "descr": "Modified TSPLIB instance for the SLAP"
        },
        "VERSION": "VRPTEST 1.0"
    },
    "NAME": "c179_f8bd",
    "NUM_VISITS": 210,
    "TIMESTEP": "1",
    "VISIT_LOCATION_SECTION": {
        "10": "114",
        "100": "136",
        "101": "390",
        "102": "456",
        "103": "152",
        "104": "56",
        "105": "320",
        "106": "254",
        "107": "313",
        "108": "96",
        "109": "115",
        "11": "249",
        "110": "214",
        "111": "341",
        "112": "29",
        "113": "305",
        "114": "75",
        "115": "202",
        "116": "28",
        "117": "110",
        "118": "13",
        "119": "306",
        "12": "73",
        "120": "213",
        "121": "27",
        "122": "364",
        "123": "31",
        "124": "95",
        "125": "450",
        "126": "231",
        "127": "365",
        "128": "161",
        "129": "376",
        "13": "58",
        "130": "41",
        "131": "85",
        "132": "169",
        "133": "98",
        "134": "440",
        "135": "335",
        "136": "269",
        "137": "383",
        "138": "240",
        "139": "17",
        "14": "160",
        "140": "454",
        "141": "372",
        "142": "194",
        "143": "192",
        "144": "170",
        "145": "227",
        "146": "87",
        "147": "462",
        "148": "2",
        "149": "433",
        "15": "144",
        "150": "42",
        "151": "180",
        "152": "216",
        "153": "64",
        "154": "288",
        "155": "389",
        "156": "107",
        "157": "195",
        "158": "183",
        "159": "394",
        "16": "159",
        "160": "222",
        "161": "45",
        "162": "26",
        "163": "362",
        "164": "243",
        "165": "101",
        "166": "191",
        "167": "278",
        "168": "229",
        "169": "99",
        "17": "166",
        "170": "187",
        "171": "378",
        "172": "396",
        "173": "16",
        "174": "324",
        "175": "211",
        "176": "127",
        "177": "321",
        "178": "208",
        "179": "21",
        "18": "193",
        "180": "18",
        "19": "238",
        "2": "33",
        "20": "32",
        "21": "132",
        "22": "100",
        "23": "435",
        "24": "311",
        "25": "174",
        "26": "186",
        "27": "140",
        "28": "172",
        "29": "316",
        "3": "23",
        "30": "135",
        "31": "354",
        "32": "163",
        "33": "142",
        "34": "153",
        "35": "414",
        "36": "452",
        "37": "325",
        "38": "34",
        "39": "447",
        "4": "120",
        "40": "55",
        "41": "244",
        "42": "239",
        "43": "198",
        "44": "129",
        "45": "221",
        "46": "253",
        "47": "68",
        "48": "255",
        "49": "94",
        "5": "5",
        "50": "156",
        "51": "78",
        "52": "371",
        "53": "121",
        "54": "168",
        "55": "164",
        "56": "236",
        "57": "369",
        "58": "446",
        "59": "413",
        "6": "263",
        "60": "102",
        "61": "201",
        "62": "82",
        "63": "426",
        "64": "209",
        "65": "356",
        "66": "388",
        "67": "247",
        "68": "283",
        "69": "279",
        "7": "167",
        "70": "83",
        "71": "219",
        "72": "54",
        "73": "37",
        "74": "466",
        "75": "44",
        "76": "405",
        "77": "50",
        "78": "409",
        "79": "256",
        "8": "392",
        "80": "89",
        "81": "363",
        "82": "69",
        "83": "455",
        "84": "336",
        "85": "339",
        "86": "276",
        "87": "63",
        "88": "151",
        "89": "301",
        "9": "412",
        "90": "291",
        "91": "138",
        "92": "402",
        "93": "131",
        "94": "134",
        "95": "331",
        "96": "225",
        "97": "328",
        "98": "458",
        "99": "126",
        "370": "304",
        "188": "79",
        "205": "145",
        "411": "97",
        "381": "338",
        "261": "326",
        "256": "203"
    },
    "PICKING_LOG": {
        "0": {
            "LOCATIONS": [
                "33",
                "23",
                "120",
                "5",
                "263"
            ],
            "SKUS": [
                "2",
                "3",
                "4",
                "5",
                "6"
            ]
        },
        "1": {
            "LOCATIONS": [
                "164",
                "236",
                "369",
                "446"
            ],
            "SKUS": [
                "55",
                "56",
                "57",
                "58"
            ]
        },
        "2": {
            "LOCATIONS": [
                "413",
                "102",
                "201"
            ],
            "SKUS": [
                "59",
                "60",
                "61"
            ]
        },
        "3": {
            "LOCATIONS": [
                "82",
                "426",
                "209"
            ],
            "SKUS": [
                "62",
                "63",
                "64"
            ]
        },
        "4": {
            "LOCATIONS": [
                "356",
                "388"
            ],
            "SKUS": [
                "65",
                "66"
            ]
        },
        "5": {
            "LOCATIONS": [
                "247",
                "283",
                "279",
                "83",
                "219",
                "54",
                "37",
                "466"
            ],
            "SKUS": [
                "67",
                "68",
                "69",
                "70",
                "71",
                "72",
                "73",
                "74"
            ]
        },
        "6": {
            "LOCATIONS": [
                "44",
                "405",
                "50"
            ],
            "SKUS": [
                "75",
                "76",
                "77"
            ]
        },
        "7": {
            "LOCATIONS": [
                "409",
                "256"
            ],
            "SKUS": [
                "78",
                "79"
            ]
        },
        "8": {
            "LOCATIONS": [
                "89",
                "363"
            ],
            "SKUS": [
                "80",
                "81"
            ]
        },
        "9": {
            "LOCATIONS": [
                "69"
            ],
            "SKUS": [
                "82"
            ]
        },
        "10": {
            "LOCATIONS": [
                "455"
            ],
            "SKUS": [
                "83"
            ]
        },
        "11": {
            "LOCATIONS": [
                "167",
                "392",
                "412",
                "114",
                "249",
                "73"
            ],
            "SKUS": [
                "7",
                "8",
                "9",
                "10",
                "11",
                "12"
            ]
        },
        "12": {
            "LOCATIONS": [
                "336"
            ],
            "SKUS": [
                "84"
            ]
        },
        "13": {
            "LOCATIONS": [
                "339",
                "276",
                "63",
                "151",
                "301"
            ],
            "SKUS": [
                "85",
                "86",
                "87",
                "88",
                "89"
            ]
        },
        "14": {
            "LOCATIONS": [
                "291",
                "138",
                "402",
                "131",
                "134",
                "336"
            ],
            "SKUS": [
                "90",
                "91",
                "92",
                "93",
                "94",
                "84"
            ]
        },
        "15": {
            "LOCATIONS": [
                "331",
                "225",
                "328",
                "458",
                "126",
                "136"
            ],
            "SKUS": [
                "95",
                "96",
                "97",
                "98",
                "99",
                "100"
            ]
        },
        "16": {
            "LOCATIONS": [
                "390",
                "456",
                "152",
                "56",
                "320"
            ],
            "SKUS": [
                "101",
                "102",
                "103",
                "104",
                "105"
            ]
        },
        "17": {
            "LOCATIONS": [
                "254",
                "313",
                "96",
                "115",
                "214",
                "341"
            ],
            "SKUS": [
                "106",
                "107",
                "108",
                "109",
                "110",
                "111"
            ]
        },
        "18": {
            "LOCATIONS": [
                "29",
                "305",
                "75",
                "202",
                "28"
            ],
            "SKUS": [
                "112",
                "113",
                "114",
                "115",
                "116"
            ]
        },
        "19": {
            "LOCATIONS": [
                "110",
                "13",
                "306",
                "213"
            ],
            "SKUS": [
                "117",
                "118",
                "119",
                "120"
            ]
        },
        "20": {
            "LOCATIONS": [
                "27",
                "364",
                "31",
                "95",
                "450",
                "231",
                "365",
                "161"
            ],
            "SKUS": [
                "121",
                "122",
                "123",
                "124",
                "125",
                "126",
                "127",
                "128"
            ]
        },
        "21": {
            "LOCATIONS": [
                "376",
                "41",
                "85",
                "169",
                "304",
                "79",
                "145",
                "263",
                "97",
                "338",
                "326",
                "96",
                "203",
                "26"
            ],
            "SKUS": [
                "129",
                "130",
                "131",
                "132",
                "370",
                "188",
                "205",
                "6",
                "411",
                "381",
                "261",
                "108",
                "256",
                "162"
            ]
        },
        "22": {
            "LOCATIONS": [
                "58",
                "160",
                "144",
                "159",
                "166",
                "193"
            ],
            "SKUS": [
                "13",
                "14",
                "15",
                "16",
                "17",
                "18"
            ]
        },
        "23": {
            "LOCATIONS": [
                "98",
                "440",
                "335",
                "269",
                "383",
                "240",
                "17",
                "454"
            ],
            "SKUS": [
                "133",
                "134",
                "135",
                "136",
                "137",
                "138",
                "139",
                "140"
            ]
        },
        "24": {
            "LOCATIONS": [
                "372",
                "194",
                "192",
                "170"
            ],
            "SKUS": [
                "141",
                "142",
                "143",
                "144"
            ]
        },
        "25": {
            "LOCATIONS": [
                "227",
                "87",
                "462",
                "2",
                "433",
                "42",
                "180"
            ],
            "SKUS": [
                "145",
                "146",
                "147",
                "148",
                "149",
                "150",
                "151"
            ]
        },
        "26": {
            "LOCATIONS": [
                "216",
                "64",
                "288",
                "389",
                "107",
                "195",
                "183",
                "394"
            ],
            "SKUS": [
                "152",
                "153",
                "154",
                "155",
                "156",
                "157",
                "158",
                "159"
            ]
        },
        "27": {
            "LOCATIONS": [
                "222",
                "45",
                "26",
                "362",
                "243",
                "101"
            ],
            "SKUS": [
                "160",
                "161",
                "162",
                "163",
                "164",
                "165"
            ]
        },
        "28": {
            "LOCATIONS": [
                "191"
            ],
            "SKUS": [
                "166"
            ]
        },
        "29": {
            "LOCATIONS": [
                "278",
                "229",
                "99",
                "187"
            ],
            "SKUS": [
                "167",
                "168",
                "169",
                "170"
            ]
        },
        "30": {
            "LOCATIONS": [
                "378",
                "396"
            ],
            "SKUS": [
                "171",
                "172"
            ]
        },
        "31": {
            "LOCATIONS": [
                "16",
                "324",
                "211",
                "127",
                "321",
                "208",
                "21",
                "18"
            ],
            "SKUS": [
                "173",
                "174",
                "175",
                "176",
                "177",
                "178",
                "179",
                "180"
            ]
        },
        "32": {
            "LOCATIONS": [
                "238",
                "32",
                "132",
                "100",
                "435",
                "311",
                "174",
                "186"
            ],
            "SKUS": [
                "19",
                "20",
                "21",
                "22",
                "23",
                "24",
                "25",
                "26"
            ]
        },
        "33": {
            "LOCATIONS": [
                "140",
                "172",
                "316",
                "135"
            ],
            "SKUS": [
                "27",
                "28",
                "29",
                "30"
            ]
        },
        "34": {
            "LOCATIONS": [
                "354",
                "163",
                "142",
                "153",
                "414",
                "452",
                "325"
            ],
            "SKUS": [
                "31",
                "32",
                "33",
                "34",
                "35",
                "36",
                "37"
            ]
        },
        "35": {
            "LOCATIONS": [
                "34",
                "447",
                "55",
                "244",
                "239"
            ],
            "SKUS": [
                "38",
                "39",
                "40",
                "41",
                "42"
            ]
        },
        "36": {
            "LOCATIONS": [
                "198",
                "129",
                "221",
                "253",
                "68",
                "255",
                "94",
                "156"
            ],
            "SKUS": [
                "43",
                "44",
                "45",
                "46",
                "47",
                "48",
                "49",
                "50"
            ]
        },
        "37": {
            "LOCATIONS": [
                "78",
                "371",
                "121",
                "168"
            ],
            "SKUS": [
                "51",
                "52",
                "53",
                "54"
            ]
        },
        "38": {
            "LOCATIONS": [
                "222",
                "45",
                "26",
                "362",
                "243",
                "101"
            ],
            "SKUS": [
                "160",
                "161",
                "162",
                "163",
                "164",
                "165"
            ]
        },
        "39": {
            "LOCATIONS": [
                "98",
                "440",
                "335",
                "269",
                "383",
                "240",
                "17",
                "454"
            ],
            "SKUS": [
                "133",
                "134",
                "135",
                "136",
                "137",
                "138",
                "139",
                "140"
            ]
        },
        "40": {
            "LOCATIONS": [
                "291",
                "138",
                "402",
                "131",
                "134"
            ],
            "SKUS": [
                "90",
                "91",
                "92",
                "93",
                "94"
            ]
        },
        "41": {
            "LOCATIONS": [
                "16",
                "324",
                "211",
                "127",
                "321",
                "208",
                "21",
                "18"
            ],
            "SKUS": [
                "173",
                "174",
                "175",
                "176",
                "177",
                "178",
                "179",
                "180"
            ]
        },
        "42": {
            "LOCATIONS": [
                "413",
                "102",
                "201"
            ],
            "SKUS": [
                "59",
                "60",
                "61"
            ]
        }
    }
}