{
    "DATA_SECTION": "",
    "HEADER": {
        "COMMENTS": {
            "Best known objective": "",
            "Computational time (s)": "",
            "descr": "Modified TSPLIB instance for the SLAP"
        },
        "VERSION": "VRPTEST 1.0"
    },
    "NAME": "c8_3bbb",
    "NUM_VISITS": 29,
    "TIMESTEP": "1",
    "VISIT_LOCATION_SECTION": {
        "2": "217",
        "3": "472",
        "4": "48",
        "5": "325",
        "6": "242",
        "7": "5",
        "8": "241",
        "9": "221",
        "43": "105",
        "19": "53",
        "145": "270",
        "471": "211",
        "319": "426",
        "261": "448",
        "226": "243",
        "177": "421",
        "397": "218",
        "393": "156"
    },
    "PICKING_LOG": {
        "0": {
            "LOCATIONS": [
                "217",
                "472",
                "48",
                "325",
                "105",
                "53",
                "270",
                "211",
                "426",
                "448",
                "243",
                "421",
                "218",
                "156"
            ],
            "SKUS": [
                "2",
                "3",
                "4",
                "5",
                "43",
                "19",
                "145",
                "471",
                "319",
                "261",
                "226",
                "177",
                "397",
                "393"
            ]
        },
        "1": {
            "LOCATIONS": [
                "242",
                "5",
                "241",
                "221",
                "325"
            ],
            "SKUS": [
                "6",
                "7",
                "8",
                "9",
                "5"
            ]
        },
        "2": {
            "LOCATIONS": [
                "242",
                "5",
                "241",
                "221"
            ],
            "SKUS": [
                "6",
                "7",
                "8",
                "9"
            ]
        },
        "3": {
            "LOCATIONS": [
                "217",
                "472",
                "48",
                "325"
            ],
            "SKUS": [
                "2",
                "3",
                "4",
                "5"
            ]
        },
        "4": {
            "LOCATIONS": [
                "242",
                "5",
                "241",
                "221"
            ],
            "SKUS": [
                "6",
                "7",
                "8",
                "9"
            ]
        },
        "5": {
            "LOCATIONS": [
                "242",
                "5",
                "241",
                "221"
            ],
            "SKUS": [
                "6",
                "7",
                "8",
                "9"
            ]
        },
        "6": {
            "LOCATIONS": [
                "217",
                "472",
                "48",
                "325"
            ],
            "SKUS": [
                "2",
                "3",
                "4",
                "5"
            ]
        }
    }
}